pydentity/__init__.py
pydentity/abc/__init__.py
pydentity/abc/__pycache__/__init__.cpython-312.pyc
pydentity/abc/__pycache__/data_protector.cpython-312.pyc
pydentity/abc/__pycache__/lookup_normalizer.cpython-312.pyc
pydentity/abc/__pycache__/password_hasher.cpython-312.pyc
pydentity/abc/__pycache__/stores.cpython-312.pyc
pydentity/abc/__pycache__/token_provider.cpython-312.pyc
pydentity/abc/__pycache__/user_claims_principal_factory.cpython-312.pyc
pydentity/abc/__pycache__/user_confirmation.cpython-312.pyc
pydentity/abc/__pycache__/validators.cpython-312.pyc
pydentity/abc/data_protector.py
pydentity/abc/lookup_normalizer.py
pydentity/abc/password_hasher.py
pydentity/abc/stores.py
pydentity/abc/token_provider.py
pydentity/abc/user_claims_principal_factory.py
pydentity/abc/user_confirmation.py
pydentity/abc/validators.py
pydentity/contrib/__init__.py
pydentity/contrib/__pycache__/__init__.cpython-312.pyc
pydentity/contrib/sqlalchemy/__init__.py
pydentity/contrib/sqlalchemy/__pycache__/__init__.cpython-312.pyc
pydentity/contrib/sqlalchemy/__pycache__/fields.cpython-312.pyc
pydentity/contrib/sqlalchemy/__pycache__/models.cpython-312.pyc
pydentity/contrib/sqlalchemy/base/__init__.py
pydentity/contrib/sqlalchemy/base/__pycache__/__init__.cpython-312.pyc
pydentity/contrib/sqlalchemy/base/__pycache__/abstract.cpython-312.pyc
pydentity/contrib/sqlalchemy/base/__pycache__/model.cpython-312.pyc
pydentity/contrib/sqlalchemy/base/abstract.py
pydentity/contrib/sqlalchemy/base/model.py
pydentity/contrib/sqlalchemy/fields.py
pydentity/contrib/sqlalchemy/models.py
pydentity/contrib/sqlalchemy/stores/__init__.py
pydentity/contrib/sqlalchemy/stores/__pycache__/__init__.cpython-312.pyc
pydentity/contrib/sqlalchemy/stores/__pycache__/role_store.cpython-312.pyc
pydentity/contrib/sqlalchemy/stores/__pycache__/user_store.cpython-312.pyc
pydentity/contrib/sqlalchemy/stores/role_store.py
pydentity/contrib/sqlalchemy/stores/user_store.py
pydentity/contrib/tortoise/__init__.py
py_identity-1.0.1.dist-info/METADATA
py_identity-1.0.1.dist-info/WHEEL
py_identity-1.0.1.dist-info/RECORD
